{
  "source_filename": "ocr_text.txt",
  "raw": "Handwritten Form\n\nPatient Enrollment Form\n\nPatients enrolled in Care receive:\n\n-A Care team of dedicated advisors available by phone or email\n\n\u00abInformation on available local suppliers that work with the patient's insurance plan\n\n\u00ab Personalized product support, educational information, tips and inspiration for better bowel care\n\nPatient Information\nFirst Narne\n\nPAULA\n\nLast Name\n\nBUTLER\n\u2018aires\nBENYON GROVE F1i5\n\ncity\n\nPARK RKHAMSTED AP &SFE54\n\nEmail Address?\n\nPAULAB4ZO@MAIL .COM\n\nPhone Number - Cell phone / landline (circle one] Date of birth Language Preference\n149830232 O408196 Gee Seca\n\nInsurance Plan name\n\nSTACLIFFESPA\n\n\"By providing an email addres the patlent consents to the feceint of personized support though Colplast_ #Core Online.\n\nYEOTAINTON\nbya\n\nLAKE CELYN\nCity\n\nCAPE RDBPEAK PT 95370\n\nClinican Name\n\nSPENCER BARKER\n\nNPI\n\nFQAQL2AFSBF\nClinican Signiture: Date XS/OR/2014-\n\nMy siginiture acknowledges that | have rad the Care Program Description and Terms of Enrollment to the patient and the patient concenced,\n\nCate Program and Description and Terms of Enrollment: Care isa patient support programm designed to provide support for patients andior caregivers who\nUse Irigation System - for as long 2s erroded individuell desire to receive that educational information from Form.\n\nCare incorporates active engagement with a dedicated Care Advisor, including direct phone andlor email support with information and guiddence on Form,\nproper use of Products, support locating a product supplier, aswell as information regarding product reimbursement,\n\n\u2018When each individual has becorne more independence and onfident with his or her product and dally routines, dedicosed Care advisors provide on-going\nrelevance, information and support via email or phone contact during the fll year of Form use. Users may receive personalled information containing articles,\n\u2018advice, inspirational stores and answers to lfestyle questions that may be of interest.\n\nBy envoling in Care independently or through your healthcare provider, | agree that Forrn may contact me by phone (including my cell phone thats the\n\u2018umber | provided) text message {sms}, e-mal, hard copy letter, or other means of communication but only for the purpose referred to above. also give Form\n\"mi petrission to interact with my healtheare provider or product supplier in connection with the Support| receive through Care,\n\nundertand that !can unsubscribe at any time if do not want to receive communication from Last related to my participation in the Care program any longer.\n| understand that to ursubserbe | may cl at 898-726-7872 or may ursubseribe at anytime by chcking the ursubserbe option st any eral receved\n\u2018through Care program.\n\n\u2018Ostamy Care / Continence Care / Wound & Skin Care\nForm Corp. Minneopolis, MN S511 1-800-513-0405\n",
  "patient": {
    "first_name": "PAULA Last Name BUTLER",
    "last_name": "BUTLER \u2018aires BENYON GROVE F1i5",
    "email": "paulab4zo@mail.com",
    "phone": null,
    "address": "BENYON GROVE F1i5 | PARK RKHAMSTED AP &SFE54 | PAULAB4ZO@MAIL .COM",
    "zip_code": "95370"
  },
  "insurance": {
    "name": "\u00ab Personalized product support, educational information, tips and inspiration for better bowel care Patient Information First Narne"
  },
  "clinician": {
    "name": "SPENCER BARKER NPI FQAQL2AFSBF",
    "npi": "FQAQL2AFSBF Clinican Signiture: Date XS/OR/2014- My siginiture acknowledges that | have rad the Care Program Description and Terms of Enrollment to the patient and the patient concenced,"
  },
  "consent_text": "By providing an email addres the patlent consents to the feceint of personized support though Colplast_ #Core Online.\n\nYEOTAINTON\nbya\n\nLAKE CELYN\nCity\n\nCAPE RDBPEAK PT 95370\n\nClinican Name\n\nSPENCER BARKER\n\nNPI\n\nFQAQL2AFSBF\nClinican Signiture: Date XS/OR/2014-\n\nMy siginiture acknowledges that | have rad the Care Program Description and Terms of Enrollment to the patient and the patient concenced,\n\nCate Program"
}